judge/__init__.py
judge/__main__.py
judge/mark_day.py
judge_markday-0.1.12.dist-info/METADATA
judge_markday-0.1.12.dist-info/WHEEL
judge_markday-0.1.12.dist-info/top_level.txt
judge_markday-0.1.12.dist-info/RECORD
