Metadata-Version: 2.4
Name: judge-markday
Version: 0.1.12
Summary: Utility for marking daily results with judge integration
Author: andrwl1
License: MIT
Project-URL: Homepage, https://github.com/andrwl1/judge-markday
Requires-Python: >=3.8
